contrakit/__init__.py
contrakit/agreement.py
contrakit/behavior/_analysis.py
contrakit/behavior/_representation.py
contrakit/behavior/agreement_api.py
contrakit/behavior/behavior.py
contrakit/constants.py
contrakit/context.py
contrakit/contradiction.py
contrakit/convex_models.py
contrakit/distribution.py
contrakit/frame.py
contrakit/lens.py
contrakit/observatory.py
contrakit/space.py
contrakit-0.0.3.dist-info/METADATA
contrakit-0.0.3.dist-info/WHEEL
contrakit-0.0.3.dist-info/licenses/LICENSE
contrakit-0.0.3.dist-info/licenses/LICENSE-CC-BY-4.0
contrakit-0.0.3.dist-info/RECORD
