Metadata-Version: 2.4
Name: contrakit
Version: 0.0.3
Summary: Epistemic modeling toolkit for quantifying information costs when valid perspectives disagree
License-File: LICENSE
License-File: LICENSE-CC-BY-4.0
Keywords: information-theory,contradiction,epistemic-modeling,quantum-contextuality,distributed-systems
Author: Cassidy Bridges
Author-email: cassidybridges@gmail.com
Requires-Python: >=3.10,<3.15
Classifier: Development Status :: 4 - Beta
Classifier: Intended Audience :: Developers
Classifier: Intended Audience :: Science/Research
Classifier: License :: OSI Approved :: MIT License
Classifier: Programming Language :: Python :: 3
Classifier: Programming Language :: Python :: 3.10
Classifier: Programming Language :: Python :: 3.11
Classifier: Programming Language :: Python :: 3.12
Classifier: Programming Language :: Python :: 3.13
Classifier: Programming Language :: Python :: 3.14
Classifier: Topic :: Scientific/Engineering :: Information Analysis
Classifier: Topic :: Scientific/Engineering :: Mathematics
Classifier: Topic :: Software Development :: Libraries :: Python Modules
Requires-Dist: cvxpy (>=1.7.2,<2.0.0)
Requires-Dist: datasets (>=4.4.1,<5.0.0)
Requires-Dist: gdown (>=5.2.0,<6.0.0)
Requires-Dist: matplotlib (>=3.10.8,<4.0.0)
Requires-Dist: numba (>=0.61.2,<0.62.0)
Requires-Dist: numpy (>=1.24.0,<2.0.0)
Requires-Dist: ollama (>=0.6.1,<0.7.0)
Requires-Dist: pandas (>=2.3.3,<3.0.0)
Requires-Dist: pytorch-ood (>=0.2.2,<0.3.0)
Requires-Dist: scs (>=3.2.8,<4.0.0)
Requires-Dist: seaborn (>=0.13.2,<0.14.0)
Requires-Dist: torch (>=2.9.1,<3.0.0)
Requires-Dist: torchvision (>=0.24.1,<0.25.0)
Requires-Dist: transformers (>=4.57.3,<5.0.0)
Project-URL: Documentation, https://github.com/off-by-some/contrakit/tree/main/docs
Project-URL: Homepage, https://github.com/off-by-some/contrakit
Project-URL: Repository, https://github.com/off-by-some/contrakit
